pysportbot/__init__.py
pysportbot/activities.py
pysportbot/authenticator.py
pysportbot/bookings.py
pysportbot/centres.py
pysportbot/endpoints.py
pysportbot/service/__init__.py
pysportbot/service/__main__.py
pysportbot/service/booking.py
pysportbot/service/config_loader.py
pysportbot/service/config_validator.py
pysportbot/service/scheduling.py
pysportbot/service/service.py
pysportbot/service/threading.py
pysportbot/session.py
pysportbot/utils/__init__.py
pysportbot/utils/errors.py
pysportbot/utils/logger.py
pysportbot/utils/time.py
pysportbot-0.0.19.dist-info/METADATA
pysportbot-0.0.19.dist-info/WHEEL
pysportbot-0.0.19.dist-info/licenses/LICENSE
pysportbot-0.0.19.dist-info/RECORD
