Metadata-Version: 2.4
Name: pysportbot
Version: 0.0.19
Summary: A python-based bot for automatic resasports slot booking
License-File: LICENSE
Author: Joshua Falco Beirer
Author-email: jbeirer@cern.ch
Requires-Python: >=3.10,<3.14
Classifier: Programming Language :: Python :: 3
Classifier: Programming Language :: Python :: 3.10
Classifier: Programming Language :: Python :: 3.11
Classifier: Programming Language :: Python :: 3.12
Classifier: Programming Language :: Python :: 3.13
Requires-Dist: beautifulsoup4 (>=4.13.5,<5.0.0)
Requires-Dist: pandas (>=2.3.2,<3.0.0)
Requires-Dist: pytz (>=2025.2,<2026.0)
Requires-Dist: requests (>=2.32.5,<3.0.0)
